quera_ahs_utils/analysis.py
quera_ahs_utils/drive.py
quera_ahs_utils/ir.py
quera_ahs_utils/parallelize.py
quera_ahs_utils/plotting.py
quera_ahs_utils/quera_ir/capabilities.py
quera_ahs_utils/quera_ir/task_results.py
quera_ahs_utils/quera_ir/task_specification.py
quera_ahs_utils-0.4.4.dist-info/LICENSE
quera_ahs_utils-0.4.4.dist-info/METADATA
quera_ahs_utils-0.4.4.dist-info/WHEEL
quera_ahs_utils-0.4.4.dist-info/top_level.txt
quera_ahs_utils-0.4.4.dist-info/RECORD
