Metadata-Version: 2.1
Name: quera-ahs-utils
Version: 0.4.4
Summary: Various tools to interact with Braket Analog Hamiltonian Computing
Author-email: Phillip Weinberg <pweinberg@quera.com>, John Long <jlong@quera.com>
Maintainer-email: Phillip Weinberg <pweinberg@quera.com>, John Long <jlong@quera.com>
Project-URL: Homepage, https://github.com/QuEraComputing/quera-ahs-utils
Project-URL: Bug Tracker, https://github.com/QuEraComputing/quera-ahs-utils/issues
Classifier: Programming Language :: Python :: 3
Classifier: Operating System :: OS Independent
Requires-Python: >=3.10
License-File: LICENSE
Requires-Dist: amazon-braket-sdk
Requires-Dist: networkx
Requires-Dist: numpy
Requires-Dist: scipy
Requires-Dist: matplotlib
Requires-Dist: pydantic >=2.0.0
